Metadata-Version: 2.1
Name: kraken_didip
Version: 0.0.1.dev2116
Summary: OCR/HTR engine for all the languages: a fork for the DiDip project.
Home-page: https://github.com/Didip-eu/kraken_didip
Author: Benjamin Kiessling
Author-email: mittagessen@l.unchti.me
Maintainer: Nicolas Renet
Maintainer-email: nicolas.renet@uni-graz.at
License: Apache
Keywords: ocr,htr
Classifier: Development Status :: 5 - Production/Stable
Classifier: Environment :: Console
Classifier: Environment :: GPU
Classifier: Intended Audience :: Science/Research
Classifier: License :: OSI Approved :: Apache Software License
Classifier: Operating System :: POSIX
Classifier: Programming Language :: Python :: 3.8
Classifier: Programming Language :: Python :: 3.9
Classifier: Programming Language :: Python :: 3.10
Classifier: Programming Language :: Python :: 3.11
Classifier: Topic :: Scientific/Engineering :: Image Recognition
Classifier: Topic :: Scientific/Engineering :: Artificial Intelligence
Requires-Python: <=3.11.99,>=3.8
License-File: LICENSE
License-File: AUTHORS
Requires-Dist: jsonschema
Requires-Dist: lxml
Requires-Dist: requests
Requires-Dist: click >=8.1
Requires-Dist: numpy ~=1.23.0
Requires-Dist: Pillow >=9.2.0
Requires-Dist: regex
Requires-Dist: scipy ~=1.10.0
Requires-Dist: protobuf >=3.0.0
Requires-Dist: coremltools ~=6.0
Requires-Dist: jinja2 ~=3.0
Requires-Dist: python-bidi ==0.4.2
Requires-Dist: torchvision >=0.5.0
Requires-Dist: torch ~=2.1.0
Requires-Dist: scikit-learn ~=1.2.1
Requires-Dist: scikit-image ~=0.21.0
Requires-Dist: shapely ~=1.8.5
Requires-Dist: pyarrow
Requires-Dist: lightning ~=2.2.0
Requires-Dist: torchmetrics >=1.1.0
Requires-Dist: threadpoolctl ~=3.4.0
Requires-Dist: importlib-resources >=1.3.0
Requires-Dist: rich
Provides-Extra: augment
Requires-Dist: albumentations ; extra == 'augment'
Provides-Extra: pdf
Requires-Dist: pyvips ; extra == 'pdf'
Provides-Extra: test
Requires-Dist: hocr-spec ; extra == 'test'
Requires-Dist: pytest ; extra == 'test'
